{
 "Bamboo Candlestick": 38,
 "Blue Celadon Candlestick": 48,
 "Brass Candlestick": 34,
 "Bronze Candlestick": 62,
 "Bronze Lamp": 6,
 "Bug Lamp": 12,
 "Burned out Torch": 1,
 "Burned-out Torch": 4,
 "Candle": 36,
 "Ceramic Candlestick": 14,
 "Ceramic Tea Warmer": 2,
 "Clay Candlestick": 116,
 "Colovian Lantern": 32,
 "Dravis' Special Lantern": 2,
 "Dwemer Lantern": 6,
 "Ebony Candlestick": 36,
 "Eerie Lantern": 4,
 "Fine Glass Candlestick": 18,
 "Frosted Ebony Candlestick": 24,
 "Gilded Red Glass Candle": 24,
 "Glass Candlestick": 16,
 "Glass Lantern": 52,
 "Glowjug": 8,
 "Gold Candlestick": 8,
 "Green Celadon Candlestick": 48,
 "Green Glass Candlestick": 76,
 "Grim Lamp": 2,
 "Indoril Lantern": 18,
 "Iron Candlestick": 28,
 "Iron Lantern": 8,
 "Lantern": 6,
 "Limeware Lamp": 2,
 "Minor Welkynd": 2,
 "Orc Lantern": 4,
 "Palmwood Candlestick": 50,
 "Paper Lantern": 126,
 "Pewter Candlestick": 45,
 "Pilgrim's Lantern": 2,
 "Radius Marker": 2,
 "Rawhide Lantern": 6,
 "Red Glass Candlestick": 58,
 "Redware Candle": 20,
 "Redware Lamp": 2,
 "Shellware Candlestick": 106,
 "Silver Candlestick": 32,
 "Stoneware Candlestick": 130,
 "The Watchman's Eye": 2,
 "Tiny Seadrake": 2,
 "Torch": 46,
 "Travel Lantern": 36,
 "Varla Stone": 2,
 "Welkynd Stone": 2,
 "Wicker Lantern": 8,
 "Wooden Lantern": 8,
 "Wooden Travel Lantern": 2
}